tahrir/__init__.py
tahrir/admin.py
tahrir/app.py
tahrir/cache.py
tahrir/cli.py
tahrir/database.py
tahrir/defaults.py
tahrir/l10n.py
tahrir/notifications.py
tahrir/sitedocs/about.rst
tahrir/sitedocs/footer.rst
tahrir/static/css/monokai.css
tahrir/static/css/tahrir.css
tahrir/static/css/unsemantic-grid-mobile.css
tahrir/static/css/unsemantic-grid-responsive-tablet.css
tahrir/static/css/unsemantic-grid-responsive.css
tahrir/static/img/404.png
tahrir/static/img/404.svg
tahrir/static/img/500.png
tahrir/static/img/500.svg
tahrir/static/img/badge.png
tahrir/static/img/badge_bullet.png
tahrir/static/img/badge_bullet_fedora.png
tahrir/static/img/badger_avatar.png
tahrir/static/img/badger_avatar.svg
tahrir/static/img/favicon.ico
tahrir/static/img/fedora_badges.png
tahrir/static/img/fedora_badges_small.png
tahrir/static/img/fedora_logo.png
tahrir/static/js/builder.js
tahrir/static/js/favico-0.3.4.min.js
tahrir/static/js/jquery-3.3.1.min.js
tahrir/static/js/social.js
tahrir/static/js/thingiview/Three.js
tahrir/static/js/thingiview/binaryReader.js
tahrir/static/js/thingiview/plane.js
tahrir/static/js/thingiview/stats.js
tahrir/static/js/thingiview/thingiloader.js
tahrir/static/js/thingiview/thingiview.js
tahrir/templates/404.html
tahrir/templates/500.html
tahrir/templates/_badge-base.html
tahrir/templates/_base.html
tahrir/templates/_functions.html
tahrir/templates/about.html
tahrir/templates/admin/index.html
tahrir/templates/admin.html
tahrir/templates/assertion_widget.html
tahrir/templates/badge.html
tahrir/templates/badge_full.html
tahrir/templates/builder.html
tahrir/templates/diff.html
tahrir/templates/explore.html
tahrir/templates/explore_badges.html
tahrir/templates/index.html
tahrir/templates/leaderboard.html
tahrir/templates/report.html
tahrir/templates/tags.html
tahrir/templates/thingiview.html
tahrir/templates/user.html
tahrir/translations/messages.pot
tahrir/utils/__init__.py
tahrir/utils/avatar.py
tahrir/utils/badge.py
tahrir/utils/date_time.py
tahrir/utils/docs.py
tahrir-2.1.0.dist-info/LICENSE
tahrir-2.1.0.dist-info/METADATA
tahrir-2.1.0.dist-info/WHEEL
tahrir-2.1.0.dist-info/RECORD
